huangningbao_mcp_server/__init__.py
huangningbao_mcp_server-0.1.0.dist-info/WHEEL
huangningbao_mcp_server-0.1.0.dist-info/entry_points.txt
huangningbao_mcp_server-0.1.0.dist-info/METADATA
huangningbao_mcp_server-0.1.0.dist-info/RECORD
